MANIFEST.in
README.txt
setup.py
docs/HISTORY.txt
src/five/__init__.py
src/five.dbevent.egg-info/PKG-INFO
src/five.dbevent.egg-info/SOURCES.txt
src/five.dbevent.egg-info/dependency_links.txt
src/five.dbevent.egg-info/namespace_packages.txt
src/five.dbevent.egg-info/not-zip-safe
src/five.dbevent.egg-info/requires.txt
src/five.dbevent.egg-info/top_level.txt
src/five/dbevent/__init__.py
src/five/dbevent/configure.zcml