Metadata-Version: 1.0
Name: five.dbevent
Version: 0.1.1
Summary: ZODB Database startup events backported to Zope 2
Home-page: http://pypi.python.org/pypi/five.dbevent
Author: Godefroid Chapelle and Jean-Francois Roche
Author-email: zope-dev@zope.org
License: ZPL
Keywords: zope2 zodb
Platform: UNKNOWN
Classifier: Programming Language :: Python
Classifier: Topic :: Software Development :: Libraries :: Python Modules
Classifier: Framework :: Zope2
